pyro_mysql-0.2.16.dist-info/METADATA
pyro_mysql-0.2.16.dist-info/WHEEL
pyro_mysql-0.2.16.dist-info/entry_points.txt
pyro_mysql.libs/libcrypto-6a19fda9.so.3
pyro_mysql.libs/libssl-f541f910.so.3
pyro_mysql/__init__.py
pyro_mysql/__init__.pyi
pyro_mysql/async_.py
pyro_mysql/async_.pyi
pyro_mysql/dbapi.py
pyro_mysql/dbapi.pyi
pyro_mysql/dbapi_async.py
pyro_mysql/dbapi_async.pyi
pyro_mysql/error.py
pyro_mysql/error.pyi
pyro_mysql/py.typed
pyro_mysql/pyro_mysql.abi3.so
pyro_mysql/sqlalchemy_async.py
pyro_mysql/sqlalchemy_sync.py
pyro_mysql/sync.py
pyro_mysql/sync.pyi
pyro_mysql/testing/__init__.py
pyro_mysql/testing/requirements.py
pyro_mysql/testing/sqlalchemy_pytest_plugin.py
pyro_mysql-0.2.16.dist-info/RECORD
