Metadata-Version: 2.4
Name: pyro-mysql
Version: 0.2.16
Classifier: Development Status :: 4 - Beta
Classifier: Intended Audience :: Developers
Classifier: License :: OSI Approved :: MIT License
Classifier: Operating System :: OS Independent
Classifier: Programming Language :: Python :: 3
Classifier: Programming Language :: Python :: 3.10
Classifier: Programming Language :: Python :: 3.11
Classifier: Programming Language :: Python :: 3.12
Classifier: Programming Language :: Python :: 3.13
Classifier: Programming Language :: Python :: 3.14
Classifier: Programming Language :: Python :: Implementation :: CPython
Classifier: Programming Language :: Python :: Free Threading :: 1 - Unstable
Classifier: Programming Language :: Rust
Classifier: Topic :: Database
Classifier: Topic :: Database :: Front-Ends
Classifier: Topic :: Software Development :: Libraries :: Python Modules
Classifier: Framework :: AsyncIO
Classifier: Typing :: Typed
Requires-Dist: pep249>=1.1.0
Requires-Dist: sqlalchemy>=2.0.44
Requires-Dist: typing-extensions>=4.0.0
Summary: High-performance MySQL driver for Python
Keywords: mysql,async,asyncio,database,rust,pyo3
License: MIT
Requires-Python: >=3.10
Project-URL: Repository, https://github.com/elbaro/pyro-mysql
